posggym/__init__.py
posggym/core.py
posggym/error.py
posggym/logger.py
posggym/model.py
posggym/py.typed
posggym/envs/__init__.py
posggym/envs/registration.py
posggym/envs/classic/__init__.py
posggym/envs/classic/mabc.py
posggym/envs/classic/rock_paper_scissors.py
posggym/envs/classic/tiger.py
posggym/envs/continous/__init__.py
posggym/envs/grid_world/__init__.py
posggym/envs/grid_world/core.py
posggym/envs/grid_world/driving.py
posggym/envs/grid_world/driving_gen.py
posggym/envs/grid_world/lbf.py
posggym/envs/grid_world/predator_prey.py
posggym/envs/grid_world/pursuit_evasion.py
posggym/envs/grid_world/render.py
posggym/envs/grid_world/two_paths.py
posggym/envs/grid_world/uav.py
posggym/envs/grid_world/img/agent.png
posggym/envs/grid_world/img/agent_white.png
posggym/envs/grid_world/img/apple.png
posggym/envs/grid_world/img/drone.png
posggym/envs/grid_world/img/house.png
posggym/envs/grid_world/img/robber.png
posggym/envs/grid_world/img/robot.png
posggym/utils/__init__.py
posggym/utils/env_checker.py
posggym/utils/history.py
posggym/utils/model_checker.py
posggym/utils/passive_env_checker.py
posggym/utils/seeding.py
posggym/wrappers/__init__.py
posggym/wrappers/env_checker.py
posggym/wrappers/flatten_observation.py
posggym/wrappers/order_enforcing.py
posggym/wrappers/petting_zoo.py
posggym/wrappers/record_video.py
posggym/wrappers/rllib_multi_agent_env.py
posggym/wrappers/time_limit.py
posggym/wrappers/monitoring/__init__.py
posggym/wrappers/monitoring/video_recorder.py
posggym-0.3.2.dist-info/LICENSE
posggym-0.3.2.dist-info/METADATA
posggym-0.3.2.dist-info/WHEEL
posggym-0.3.2.dist-info/top_level.txt
posggym-0.3.2.dist-info/RECORD
