Metadata-Version: 2.1
Name: posggym
Version: 0.3.2
Summary: A standard API and diverse set of reference environments for reinforcement learning and planning in Partially Observable Stochastic Games (POSGs).
Author-email: Jonathon Schwartz <jonathon.schwartz@anu.edu.au>
License: MIT License
Project-URL: Homepage, https://github.com/RDLLab/posggym
Project-URL: Repository, https://github.com/RDLLab/posggym/
Project-URL: Documentation, https://posggym.readthedocs.io/
Project-URL: Bug Report, https://github.com/RDLLab/posggym/issues
Keywords: reinforcement learning,game,RL,AI,planning,posg
Classifier: Development Status :: 4 - Beta
Classifier: License :: OSI Approved :: MIT License
Classifier: Programming Language :: Python :: 3
Classifier: Programming Language :: Python :: 3.8
Classifier: Programming Language :: Python :: 3.9
Classifier: Programming Language :: Python :: 3.10
Classifier: Programming Language :: Python :: 3.11
Classifier: Intended Audience :: Science/Research
Classifier: Topic :: Scientific/Engineering :: Artificial Intelligence
Requires-Python: >=3.8
License-File: LICENSE
Requires-Dist: gymnasium (>=0.26)
Requires-Dist: numpy (>=1.21.0)
Requires-Dist: typing-extensions (>=4.3.0)
Requires-Dist: importlib-metadata (>=4.8.0) ; python_version < "3.10"
Provides-Extra: all
Requires-Dist: pygame (>=2.0) ; extra == 'all'
Provides-Extra: continuous
Requires-Dist: pygame (>=2.0) ; extra == 'continuous'
Provides-Extra: grid-world
Requires-Dist: pygame (>=2.0) ; extra == 'grid-world'
Provides-Extra: pettingzoo
Requires-Dist: pettingzoo (>=1.22) ; extra == 'pettingzoo'
Provides-Extra: rllib
Requires-Dist: ray[rllib] (>=2.3) ; extra == 'rllib'
Provides-Extra: testing
Requires-Dist: pytest (>=7.2) ; extra == 'testing'
